xplai/__init__.py
xplai/configuration.py
xplai/data_queue.py
xplai/task.py
xplai/utils.py
xplai/api/annotation_api_client.py
xplai/api/auth_api_client.py
xplai/api/concept_api_client.py
xplai/api/data_api_client.py
xplai/api/modality_api_client.py
xplai/api/task_api_client.py
xplai/cli/annotations.py
xplai/cli/auth.py
xplai/cli/cli.py
xplai/cli/concept.py
xplai/cli/modality.py
xplai/cli/task.py
xplai/cli/utils.py
xplai-0.1.9.dist-info/METADATA
xplai-0.1.9.dist-info/WHEEL
xplai-0.1.9.dist-info/entry_points.txt
xplai-0.1.9.dist-info/top_level.txt
xplai-0.1.9.dist-info/RECORD
